{
    "categories" : [
         { "name" : "Customization", "id": "customization",
           "items": [
                { "name": "Editor Options", "text" : "Use options to customize the editor", "url": "options.html"},
                { "name": "Toolbox customization", "text" : "Fully control your Question Toolbox", "url": "toolboxcustomization.html"},
                { "name": "Add properties", "text" : "Add a new property to any object", "url": "addproperties.html"},
                { "name": "Remove properties", "text" : "Remove a property explicity or use an event", "url": "removeproperties.html"}
            ]},
            { "name": "Load/Save Surveys", "id": "load-save",
              "items": [
                {"name": "Set and save survey","text":  "Show how to set and save a survey", "url": "setsurvey.html"},
                {"name": "Load Survey from Service", "text": "Load a survey from the service", "url": "loadfromservice.html"}
            ]}
        ]
}        